xaitk_saliency/__init__.py
xaitk_saliency/exceptions.py
xaitk_saliency/impls/__init__.py
xaitk_saliency/impls/gen_classifier_conf_sal/__init__.py
xaitk_saliency/impls/gen_classifier_conf_sal/mc_rise_scoring.py
xaitk_saliency/impls/gen_classifier_conf_sal/occlusion_scoring.py
xaitk_saliency/impls/gen_classifier_conf_sal/rise_scoring.py
xaitk_saliency/impls/gen_classifier_conf_sal/squared_difference_scoring.py
xaitk_saliency/impls/gen_descriptor_sim_sal/__init__.py
xaitk_saliency/impls/gen_descriptor_sim_sal/similarity_scoring.py
xaitk_saliency/impls/gen_detector_prop_sal/__init__.py
xaitk_saliency/impls/gen_detector_prop_sal/drise_scoring.py
xaitk_saliency/impls/gen_image_classifier_blackbox_sal/__init__.py
xaitk_saliency/impls/gen_image_classifier_blackbox_sal/mc_rise.py
xaitk_saliency/impls/gen_image_classifier_blackbox_sal/occlusion_based.py
xaitk_saliency/impls/gen_image_classifier_blackbox_sal/rise.py
xaitk_saliency/impls/gen_image_classifier_blackbox_sal/slidingwindow.py
xaitk_saliency/impls/gen_image_similarity_blackbox_sal/__init__.py
xaitk_saliency/impls/gen_image_similarity_blackbox_sal/occlusion_based.py
xaitk_saliency/impls/gen_image_similarity_blackbox_sal/sbsm.py
xaitk_saliency/impls/gen_object_detector_blackbox_sal/__init__.py
xaitk_saliency/impls/gen_object_detector_blackbox_sal/drise.py
xaitk_saliency/impls/gen_object_detector_blackbox_sal/occlusion_based.py
xaitk_saliency/impls/perturb_image/__init__.py
xaitk_saliency/impls/perturb_image/mc_rise.py
xaitk_saliency/impls/perturb_image/random_grid.py
xaitk_saliency/impls/perturb_image/rise.py
xaitk_saliency/impls/perturb_image/sliding_radial.py
xaitk_saliency/impls/perturb_image/sliding_window.py
xaitk_saliency/impls/saliency_metric/__init__.py
xaitk_saliency/impls/saliency_metric/entropy.py
xaitk_saliency/interfaces/__init__.py
xaitk_saliency/interfaces/gen_classifier_conf_sal.py
xaitk_saliency/interfaces/gen_descriptor_sim_sal.py
xaitk_saliency/interfaces/gen_detector_prop_sal.py
xaitk_saliency-0.14.1.dist-info/LICENSE
xaitk_saliency-0.14.1.dist-info/LICENSE.old
xaitk_saliency-0.14.1.dist-info/METADATA
xaitk_saliency-0.14.1.dist-info/WHEEL
xaitk_saliency-0.14.1.dist-info/entry_points.txt
xaitk_saliency-0.14.1.dist-info/RECORD
