Metadata-Version: 2.1
Name: xaitk-saliency
Version: 0.14.1
Summary: Visual saliency map generation interfaces and baseline implementations for explainable AI.
License: Apache-2.0
Author: Kitware, Inc.
Author-email: xaitk@kitware.com
Requires-Python: >=3.10,<4.0
Classifier: Development Status :: 3 - Alpha
Classifier: Intended Audience :: Developers
Classifier: Intended Audience :: Science/Research
Classifier: License :: OSI Approved :: Apache Software License
Classifier: Operating System :: MacOS :: MacOS X
Classifier: Operating System :: Unix
Classifier: Programming Language :: Python :: 3
Classifier: Programming Language :: Python :: 3.10
Classifier: Programming Language :: Python :: 3.11
Classifier: Programming Language :: Python :: 3.12
Classifier: Programming Language :: Python :: 3.13
Provides-Extra: example-deps
Provides-Extra: tools
Requires-Dist: click (>=8.0.3)
Requires-Dist: kwcoco (>=0.2.18) ; extra == "tools"
Requires-Dist: matplotlib (>=3.4.1) ; extra == "example-deps" or extra == "tools"
Requires-Dist: notebook (>=7.2.2) ; extra == "example-deps"
Requires-Dist: numpy (>=1.25,<2.0) ; python_version < "3.12"
Requires-Dist: numpy (>=2.1) ; python_version >= "3.13"
Requires-Dist: papermill (>=2.3.3) ; extra == "example-deps"
Requires-Dist: scikit-image (>=0.25)
Requires-Dist: scikit-learn (>=1.7.0)
Requires-Dist: scipy (>=1.15.0)
Requires-Dist: setuptools (>=78.1.1)
Requires-Dist: smqtk-classifier (>=0.20.0)
Requires-Dist: smqtk-core (>=0.20.0)
Requires-Dist: smqtk-descriptors (>=0.20.0)
Requires-Dist: smqtk-detection (>=0.23.0)
Requires-Dist: torch (>=2.2.0) ; extra == "example-deps"
Requires-Dist: torchvision (>=0.10.0) ; extra == "example-deps"
Requires-Dist: tqdm (>=4.66.3) ; extra == "example-deps"
Project-URL: Documentation, https://xaitk-saliency.readthedocs.io/
